auroracap/__init__.py
auroracap/conversations.py
auroracap/model.py
auroracap/tome.py
auroracap/utils.py
auroracap/modules/__init__.py
auroracap/modules/dispatch/__init__.py
auroracap/modules/dispatch/attention.py
auroracap/modules/dispatch/baichuan.py
auroracap/modules/dispatch/cohere.py
auroracap/modules/dispatch/deepseek_v2.py
auroracap/modules/dispatch/internlm.py
auroracap/modules/dispatch/internlm2.py
auroracap/modules/dispatch/llama.py
auroracap/modules/dispatch/mistral.py
auroracap/modules/dispatch/phi3.py
auroracap/modules/dispatch/qwen2.py
auroracap/modules/dispatch/utils.py
auroracap/modules/dispatch/yi.py
auroracap/modules/dispatch/triton_kernels/__init__.py
auroracap/modules/dispatch/triton_kernels/layer_norm.py
auroracap/modules/dispatch/triton_kernels/rms_norm.py
auroracap/modules/dispatch/triton_kernels/rotary.py
auroracap/modules/projector/__init__.py
auroracap/modules/projector/configuration_projector.py
auroracap/modules/projector/modeling_projector.py
auroracap-0.0.5.dist-info/METADATA
auroracap-0.0.5.dist-info/WHEEL
auroracap-0.0.5.dist-info/licenses/LICENSE
auroracap-0.0.5.dist-info/RECORD
