Metadata-Version: 2.3
Name: auroracap
Version: 0.0.5
Summary: Source code of AuroraCap
Project-URL: Homepage, https://huggingface.co/Reself/AuroraCap-7B-VID
Project-URL: Issues, https://huggingface.co/Reself/AuroraCap-7B-VID
Author-email: Wenhao Chai <reselfchai@gmail.com>
License-File: LICENSE
Classifier: License :: OSI Approved :: MIT License
Classifier: Operating System :: OS Independent
Classifier: Programming Language :: Python :: 3
Requires-Python: >=3.8
